state_of_mika/README.md
state_of_mika/__init__.py
state_of_mika/cli.py
state_of_mika/connector.py
state_of_mika/installer.py
state_of_mika/launcher.py
state_of_mika/mika_adapter.py
state_of_mika/registry.py
state_of_mika/som_agent.py
state_of_mika/adapters/__init__.py
state_of_mika/adapters/mock.py
state_of_mika/registry/servers.json
state_of_mika-0.2.2.dist-info/licenses/LICENSE
state_of_mika-0.2.2.dist-info/METADATA
state_of_mika-0.2.2.dist-info/WHEEL
state_of_mika-0.2.2.dist-info/entry_points.txt
state_of_mika-0.2.2.dist-info/top_level.txt
state_of_mika-0.2.2.dist-info/RECORD
