Metadata-Version: 2.4
Name: state-of-mika
Version: 0.2.2
Summary: A streamlined connector for Language Models to interact with MCP servers
Home-page: https://github.com/state-of-mika/sdk
Author: State of Mika Team
Author-email: State of Mika Team <info@stateofmika.com>
License: MIT License
Project-URL: Homepage, https://github.com/stateofmika/state-of-mika
Project-URL: Bug Tracker, https://github.com/stateofmika/state-of-mika/issues
Classifier: Development Status :: 3 - Alpha
Classifier: Intended Audience :: Developers
Classifier: License :: OSI Approved :: MIT License
Classifier: Programming Language :: Python :: 3
Classifier: Programming Language :: Python :: 3.8
Classifier: Programming Language :: Python :: 3.9
Classifier: Programming Language :: Python :: 3.10
Classifier: Programming Language :: Python :: 3.11
Requires-Python: >=3.8
License-File: LICENSE
Requires-Dist: aiohttp>=3.8.0
Requires-Dist: pyyaml>=6.0
Requires-Dist: anthropic>=0.15.0
Provides-Extra: dev
Requires-Dist: pytest>=7.0.0; extra == "dev"
Requires-Dist: pytest-asyncio>=0.21.0; extra == "dev"
Requires-Dist: black>=23.0.0; extra == "dev"
Requires-Dist: mypy>=1.0.0; extra == "dev"
Dynamic: author
Dynamic: home-page
Dynamic: license-file
Dynamic: requires-python
